{
  "last_updated": "2025-07-06T20:34:20.383408",
  "date_ranges": {
    "Last 7 days": {
      "sales_chart": {
        "labels": [
          "June 2025",
          "July 2025"
        ],
        "data": [
          88.99,
          0.0
        ],
        "type": "line",
        "title": "Sales Over Time (Last 7 days)"
      },
      "orders_chart": {
        "labels": [
          "June 2025",
          "July 2025"
        ],
        "data": [
          2,
          1
        ],
        "type": "bar",
        "title": "Orders by Month (Last 7 days)"
      }
    },
    "Last 30 days": {
      "sales_chart": {
        "labels": [
          "June 2025",
          "July 2025"
        ],
        "data": [
          855.98,
          0.0
        ],
        "type": "line",
        "title": "Sales Over Time (Last 30 days)"
      },
      "orders_chart": {
        "labels": [
          "June 2025",
          "July 2025"
        ],
        "data": [
          6,
          1
        ],
        "type": "bar",
        "title": "Orders by Month (Last 30 days)"
      }
    },
    "Last 3 months": {
      "sales_chart": {
        "labels": [
          "April 2025",
          "May 2025",
          "June 2025",
          "July 2025"
        ],
        "data": [
          578.0,
          93.98,
          1354.98,
          0.0
        ],
        "type": "line",
        "title": "Sales Over Time (Last 3 months)"
      },
      "orders_chart": {
        "labels": [
          "April 2025",
          "May 2025",
          "June 2025",
          "July 2025"
        ],
        "data": [
          2,
          3,
          7,
          1
        ],
        "type": "bar",
        "title": "Orders by Month (Last 3 months)"
      }
    },
    "Last 6 months": {
      "sales_chart": {
        "labels": [
          "January 2025",
          "February 2025",
          "March 2025",
          "April 2025",
          "May 2025",
          "June 2025",
          "July 2025"
        ],
        "data": [
          69.0,
          756.98,
          557.99,
          585.99,
          93.98,
          1354.98,
          0.0
        ],
        "type": "line",
        "title": "Sales Over Time (Last 6 months)"
      },
      "orders_chart": {
        "labels": [
          "January 2025",
          "February 2025",
          "March 2025",
          "April 2025",
          "May 2025",
          "June 2025",
          "July 2025"
        ],
        "data": [
          1,
          3,
          3,
          3,
          3,
          7,
          1
        ],
        "type": "bar",
        "title": "Orders by Month (Last 6 months)"
      }
    },
    "Last 12 months": {
      "sales_chart": {
        "labels": [
          "January 2025",
          "February 2025",
          "March 2025",
          "April 2025",
          "May 2025",
          "June 2025",
          "July 2025"
        ],
        "data": [
          548.0,
          756.98,
          557.99,
          585.99,
          93.98,
          1354.98,
          0.0
        ],
        "type": "line",
        "title": "Sales Over Time (Last 12 months)"
      },
      "orders_chart": {
        "labels": [
          "January 2025",
          "February 2025",
          "March 2025",
          "April 2025",
          "May 2025",
          "June 2025",
          "July 2025"
        ],
        "data": [
          2,
          3,
          3,
          3,
          3,
          7,
          1
        ],
        "type": "bar",
        "title": "Orders by Month (Last 12 months)"
      }
    },
    "All time": {
      "sales_chart": {
        "labels": [
          "January 2025",
          "February 2025",
          "March 2025",
          "April 2025",
          "May 2025",
          "June 2025",
          "July 2025"
        ],
        "data": [
          548.0,
          756.98,
          557.99,
          585.99,
          93.98,
          1354.98,
          0.0
        ],
        "type": "line",
        "title": "Sales Over Time (All time)"
      },
      "orders_chart": {
        "labels": [
          "January 2025",
          "February 2025",
          "March 2025",
          "April 2025",
          "May 2025",
          "June 2025",
          "July 2025"
        ],
        "data": [
          2,
          3,
          3,
          3,
          3,
          7,
          1
        ],
        "type": "bar",
        "title": "Orders by Month (All time)"
      }
    }
  },
  "static_charts": {
    "products_chart": {
      "labels": [
        "essentials",
        "note",
        "write",
        "type"
      ],
      "data": [
        4,
        3,
        3,
        2
      ],
      "type": "doughnut",
      "title": "Products by Category"
    },
    "top_customers": {
      "labels": [
        "Maria Santos",
        "Ana Costa",
        "Pedro Oliveira",
        "Marta Almeida",
        "Inês Martins",
        "João Silva",
        "Tiago Pereira",
        "Miguel Fernandes",
        "Carlos Mendes",
        "Sofia Rodrigues"
      ],
      "data": [
        987.99,
        607.0,
        558.0,
        537.99,
        479.0,
        234.99,
        168.0,
        139.97,
        103.99,
        61.0
      ],
      "type": "horizontal_bar",
      "title": "Top Customers by Spending"
    }
  },
  "filters": {
    "date_ranges": [
      "Last 7 days",
      "Last 30 days",
      "Last 3 months",
      "Last 6 months",
      "Last 12 months",
      "All time"
    ],
    "categories": [
      "essentials",
      "note",
      "write",
      "type"
    ]
  }
}